{ "stockname": "太化股份"
, "stockcode": "sh600281"
, "focusdate":"2015-07-10"
, "focusprice":"6.38"
, "buydate":"null"
, "buyprice":"0.0"
, "selldate":"null"
, "sellprice":"0.0"
, "industry":"化工行业"
, "focusdate":"2015-07-10"
, "focusprice":"6.38"
, "close":"6.38"
, "low":"6.08"
, "expectedBuyPrice":"5.68"
, "expectedSellPrice":"6.38"
, "buyDate":"null"
, "actualBuyPrice":"0.0"
, "sellDate":"null"
, "actualSellPrice":"0.0"
, "data":[
[1436112000000,8.65,8.67,7.16,7.16,28600000,7.95,0.9006,1.4518,"2015-07-06"],
[1436198400000,6.46,6.6,6.44,6.44,5650000,7.16,0.8994,0.1976,"2015-07-07"],
[1436284800000,5.8,5.8,5.8,5.8,362300,6.44,0.9006,0.0641,"2015-07-08"],
[1436457600000,6.38,6.38,6.08,6.38,16300000,5.8,1.1,44.9903,"2015-07-10"],
[0,0,0,0,0,0]]}