{ "stockname": "首航节能"
, "stockcode": "sz002665"
, "focusdate":"2015-05-04"
, "focusprice":"27.16"
, "buydate":"null"
, "buyprice":"0.0"
, "selldate":"null"
, "sellprice":"0.0"
, "industry":"机械行业"
, "focusdate":"2015-05-04"
, "focusprice":"27.16"
, "close":"24.6"
, "low":"24.28"
, "expectedBuyPrice":"24.17"
, "expectedSellPrice":"27.43"
, "buyDate":"null"
, "actualBuyPrice":"0.0"
, "sellDate":"null"
, "actualSellPrice":"0.0"
, "data":[
[1430668800000,28.3,28.45,26.9,27.16,33800000,25.86,1.0503,3.8851,"2015-05-04"],
[1430755200000,26.9,27.38,24.8,25.18,22300000,27.16,0.9271,0.6598,"2015-05-05"],
[1430841600000,25.52,25.68,24.28,24.6,16600000,25.18,0.977,0.7444,"2015-05-06"],
[0,0,0,0,0,0]]}